fusion/__init__.py
fusion/annotations.py
fusion/application.py
fusion/context.py
fusion/di.py
fusion/endpoints.py
fusion/exceptions.py
fusion/resolvers.py
fusion/routing.py
fusion-0.1.0.dist-info/METADATA
fusion-0.1.0.dist-info/WHEEL
fusion-0.1.0.dist-info/licenses/LICENSE.md
fusion-0.1.0.dist-info/RECORD
