Metadata-Version: 2.4
Name: fusion
Version: 0.1.0
Summary: Fusion is a modern ASGI web framework for Python with built-in dependency injection, OpenAPI schema generation, and MCP support.
Project-URL: Homepage, https://github.com/okanakbulut/fusion
Author: Okan Akbulut
License-File: LICENSE.md
Requires-Python: >=3.12
Requires-Dist: msgspec==0.19.0
Requires-Dist: starlette==0.47.0
Provides-Extra: dev
Requires-Dist: commitizen==4.8.2; extra == 'dev'
Requires-Dist: coverage[toml]>=6.5; extra == 'dev'
Requires-Dist: httpx; extra == 'dev'
Requires-Dist: ipython; extra == 'dev'
Requires-Dist: pre-commit==4.2.0; extra == 'dev'
Requires-Dist: pytest; extra == 'dev'
Requires-Dist: pytest-asyncio; extra == 'dev'
Requires-Dist: pytest-cov; extra == 'dev'
Requires-Dist: pytest-mock; extra == 'dev'
Requires-Dist: ruff==0.11.12; extra == 'dev'
